mardblog/__init__.py
mardblog/cli.py
mardblog-0.1.0.dist-info/METADATA
mardblog-0.1.0.dist-info/WHEEL
mardblog-0.1.0.dist-info/entry_points.txt
mardblog-0.1.0.dist-info/licenses/LICENSE
mardblog-0.1.0.dist-info/RECORD
