Metadata-Version: 2.4
Name: mardblog
Version: 0.1.0
Summary: A CLI tool that converts Markdown files to HTML with customizable CSS class names
Project-URL: Homepage, https://github.com/derekbantel/mardblog
Project-URL: Repository, https://github.com/derekbantel/mardblog
Author: Mardblog Contributors
License: MIT
License-File: LICENSE
Keywords: cli,converter,css,html,markdown
Classifier: Development Status :: 4 - Beta
Classifier: Environment :: Console
Classifier: Intended Audience :: Developers
Classifier: License :: OSI Approved :: MIT License
Classifier: Operating System :: OS Independent
Classifier: Programming Language :: Python :: 3
Classifier: Programming Language :: Python :: 3.9
Classifier: Programming Language :: Python :: 3.10
Classifier: Programming Language :: Python :: 3.11
Classifier: Programming Language :: Python :: 3.12
Classifier: Programming Language :: Python :: 3.13
Classifier: Programming Language :: Python :: 3.14
Classifier: Topic :: Documentation
Classifier: Topic :: Software Development :: Documentation
Classifier: Topic :: Text Processing :: Markup :: Markdown
Requires-Python: >=3.9
Requires-Dist: requests>=2.32.5
